{
  "classrooms" : [ {
    "id" : 1,
    "title" : "CS101",
    "description" : "Intro",
    "code" : "CS1",
    "createdBy" : "bob@example.com",
    "studentIds" : [ 8, 10 ],
    "groupCodes" : [ ]
  }, {
    "id" : 1,
    "title" : "Math",
    "description" : "MATH101",
    "code" : "Intro",
    "createdBy" : "test@example.com",
    "studentIds" : [ 1 ],
    "groupCodes" : [ ]
  }, {
    "id" : 2,
    "title" : "Math",
    "description" : "Basic Math",
    "code" : "MATH101",
    "createdBy" : "charlie@example.com",
    "studentIds" : [ ],
    "groupCodes" : [ ]
  } ]
}